sdist_check.py
sdist_check-0.1.dist-info/DESCRIPTION.rst
sdist_check-0.1.dist-info/METADATA
sdist_check-0.1.dist-info/RECORD
sdist_check-0.1.dist-info/WHEEL
sdist_check-0.1.dist-info/entry_points.txt
sdist_check-0.1.dist-info/metadata.json
sdist_check-0.1.dist-info/namespace_packages.txt
sdist_check-0.1.dist-info/top_level.txt
