Metadata-Version: 2.0
Name: sdist-check
Version: 0.1
Summary: setuptools sdist checker.
Home-page: https://github.com/ulif/sdist_check/
Author: Uli Fouquet
Author-email: uli@gnufix.de
License: MIT
Keywords: setuptools sdist check
Platform: UNKNOWN
Classifier: Development Status :: 3 - Alpha
Classifier: Environment :: Console
Classifier: Intended Audience :: System Administrators
Classifier: Topic :: Utilities
Classifier: License :: OSI Approved :: MIT License
Classifier: Programming Language :: Python :: 2
Classifier: Programming Language :: Python :: 2.7
Classifier: Programming Language :: Python :: 3
Classifier: Programming Language :: Python :: 3.3
Classifier: Programming Language :: Python :: 3.4
Classifier: Programming Language :: Python :: 3.5
Classifier: Programming Language :: Python :: Implementation :: CPython
Requires-Dist: setuptools
Provides-Extra: docs
Requires-Dist: Sphinx; extra == 'docs'
Provides-Extra: tests
Requires-Dist: docutils; extra == 'tests'
Requires-Dist: pytest (>=2.0.3); extra == 'tests'
Requires-Dist: pytest-cov; extra == 'tests'
Requires-Dist: pytest-xdist; extra == 'tests'
